{
  "tasks": {
    "sync": "slash-up sync",
    "sync:dev": "slash-up sync -e development",
    "generate": "prisma generate",
    "start": "cd src && bun run ./index.js",
    "dev": "bun --watch --no-clear-screen run ./src/index.js",
    "check": "tsc --noEmit",
    "prettier:check": "prettier ./src --check",
    "eslint:check": "eslint ./src/**/*.ts",
    "prettier:fix": "prettier ./src --write",
    "eslint:fix": "eslint ./src/**/*.ts --fix",
    "lint": "prettier ./src --check && eslint ./src/**/*.ts && tsc --noEmit",
    "lint:fix": "prettier ./src --write && eslint ./src/**/*.ts --fix"
  },
  "imports": {
    "dotenv": "https://deno.land/x/dotenv@v3.2.0/load.ts"
  },
}
